sourcerer/__init__.py
sourcerer/base.py
sourcerer/callables.py
sourcerer/engine.py
sourcerer/modules.py
sourcerer/parser.py
sourcerer/simple_statements.py
sourcerer/syntaxes.py
sourcerer-1.0b10.dist-info/DESCRIPTION.rst
sourcerer-1.0b10.dist-info/METADATA
sourcerer-1.0b10.dist-info/metadata.json
sourcerer-1.0b10.dist-info/RECORD
sourcerer-1.0b10.dist-info/top_level.txt
sourcerer-1.0b10.dist-info/WHEEL
