Metadata-Version: 2.0
Name: sourcerer
Version: 1.0b10
Summary: Library to programatically genrate python source code
Home-page: https://github.com/LISTERINE/sourcerer
Author: Jonathan Ferretti
Author-email: jon@jonathanferretti.com
License: Apache2
Keywords: sourcerer
Platform: UNKNOWN
Classifier: Development Status :: 4 - Beta
Classifier: Intended Audience :: Developers
Classifier: License :: OSI Approved :: Apache Software License
Classifier: Natural Language :: English
Classifier: Programming Language :: Python :: 2
Classifier: Programming Language :: Python :: 2.6
Classifier: Programming Language :: Python :: 2.7
Classifier: Programming Language :: Python :: 3
Classifier: Programming Language :: Python :: 3.3
Classifier: Programming Language :: Python :: 3.4
Requires-Dist: pyaml
Requires-Dist: yapf
